octodns_netbox/__init__.py
octodns_netbox/reversename.py
octodns_netbox-0.5.0.dist-info/METADATA
octodns_netbox-0.5.0.dist-info/WHEEL
octodns_netbox-0.5.0.dist-info/licenses/LICENSE
octodns_netbox-0.5.0.dist-info/RECORD
