Metadata-Version: 2.4
Name: octodns-netbox
Version: 0.5.0
Summary: A NetBox source for octoDNS.
License-Expression: MIT
License-File: LICENSE
Author: Tagawa, Masaki
Author-email: masaki@tagawa.email
Requires-Python: >=3.10,<4
Classifier: Development Status :: 4 - Beta
Classifier: Intended Audience :: Developers
Classifier: License :: OSI Approved :: MIT License
Classifier: Natural Language :: English
Classifier: Programming Language :: Python :: 3
Classifier: Programming Language :: Python :: 3.10
Classifier: Programming Language :: Python :: 3.11
Classifier: Programming Language :: Python :: 3.12
Classifier: Programming Language :: Python :: 3.13
Classifier: Programming Language :: Python :: 3.14
Requires-Dist: octodns (>=1.10.0,<2.0.0)
Requires-Dist: pydantic (>=2.10.5,<3.0.0)
Requires-Dist: pynetbox (>=7.4.1,<8.0.0)
Requires-Dist: requests (>=2.32.3,<3.0.0)
